mps_bitsandbytes/_C.cpython-314-darwin.so
mps_bitsandbytes/__init__.py
mps_bitsandbytes/functional.py
mps_bitsandbytes/integration.py
mps_bitsandbytes/csrc/mps_bitsandbytes.mm
mps_bitsandbytes/kernels/fp4_matmul.metal
mps_bitsandbytes/kernels/fp8_matmul.metal
mps_bitsandbytes/kernels/int8_mm.metal
mps_bitsandbytes/kernels/nf4_matmul.metal
mps_bitsandbytes/nn/__init__.py
mps_bitsandbytes/nn/embedding.py
mps_bitsandbytes/nn/linear4bit.py
mps_bitsandbytes/nn/linear8bit.py
mps_bitsandbytes/nn/linear_fp8.py
mps_bitsandbytes/nn/outlier_aware.py
mps_bitsandbytes/nn/switchback.py
mps_bitsandbytes/optim/__init__.py
mps_bitsandbytes/optim/adam8bit.py
mps_bitsandbytes/optim/lion8bit.py
mps_bitsandbytes/optim/paged.py
mps_bitsandbytes/optim/sgd8bit.py
mps_bitsandbytes-0.5.0.dist-info/METADATA
mps_bitsandbytes-0.5.0.dist-info/WHEEL
mps_bitsandbytes-0.5.0.dist-info/top_level.txt
mps_bitsandbytes-0.5.0.dist-info/RECORD
