Metadata-Version: 2.4
Name: mps-bitsandbytes
Version: 0.5.0
Summary: NF4/FP4/FP8/INT8 quantization for PyTorch on Apple Silicon with Metal GPU acceleration
Author: imperatormk
License-Expression: MIT
Project-URL: Homepage, https://github.com/mpsops/mps-bitsandbytes
Project-URL: Repository, https://github.com/mpsops/mps-bitsandbytes
Project-URL: Issues, https://github.com/mpsops/mps-bitsandbytes/issues
Project-URL: Documentation, https://github.com/mpsops/mps-bitsandbytes#readme
Keywords: quantization,4bit,8bit,nf4,qlora,apple-silicon,pytorch,mps,metal,bitsandbytes,llm,transformers
Classifier: Development Status :: 4 - Beta
Classifier: Intended Audience :: Developers
Classifier: Intended Audience :: Science/Research
Classifier: Operating System :: MacOS :: MacOS X
Classifier: Programming Language :: Python :: 3
Classifier: Programming Language :: Python :: 3.10
Classifier: Programming Language :: Python :: 3.11
Classifier: Programming Language :: Python :: 3.12
Classifier: Topic :: Scientific/Engineering :: Artificial Intelligence
Requires-Python: >=3.10
Requires-Dist: torch>=2.0.0
Provides-Extra: dev
Requires-Dist: pytest>=7.0; extra == "dev"
Requires-Dist: pytest-cov; extra == "dev"
Provides-Extra: transformers
Requires-Dist: transformers>=4.30.0; extra == "transformers"
Requires-Dist: accelerate>=0.20.0; extra == "transformers"
Dynamic: requires-python
